{"id":"cc2e5b62-a6c6-455b-adb0-deaf3b142bc9","revision":0,"last_node_id":16,"last_link_id":25,"nodes":[{"id":8,"type":"VAEDecode","pos":[1225.9786376953125,288.5720520019531],"size":[210,46],"flags":{},"order":5,"mode":0,"inputs":[{"localized_name":"samples","name":"samples","type":"LATENT","link":17},{"localized_name":"vae","name":"vae","type":"VAE","link":8}],"outputs":[{"localized_name":"IMAGE","name":"IMAGE","type":"IMAGE","slot_index":0,"links":[9]}],"properties":{"cnr_id":"comfy-core","ver":"0.3.51","Node name for S&R":"VAEDecode"},"widgets_values":[]},{"id":4,"type":"CheckpointLoaderSimple","pos":[-218.9209747314453,356.29510498046875],"size":[315,98],"flags":{},"order":0,"mode":0,"inputs":[{"localized_name":"ckpt_name","name":"ckpt_name","type":"COMBO","widget":{"name":"ckpt_name"},"link":null}],"outputs":[{"localized_name":"MODEL","name":"MODEL","type":"MODEL","slot_index":0,"links":[1]},{"localized_name":"CLIP","name":"CLIP","type":"CLIP","slot_index":1,"links":[22,24]},{"localized_name":"VAE","name":"VAE","type":"VAE","slot_index":2,"links":[8]}],"properties":{"cnr_id":"comfy-core","ver":"0.3.51","Node name for S&R":"CheckpointLoaderSimple","models":[{"name":"v1-5-pruned-emaonly-fp16.safetensors","url":"https://huggingface.co/Comfy-Org/stable-diffusion-v1-5-archive/resolve/main/v1-5-pruned-emaonly-fp16.safetensors?download=true","directory":"checkpoints"}]},"widgets_values":["juggernautXL_ragnarokBy.safetensors"]},{"id":5,"type":"EmptyLatentImage","pos":[314.4631652832031,681.044677734375],"size":[315,106],"flags":{},"order":1,"mode":0,"inputs":[{"localized_name":"width","name":"width","type":"INT","widget":{"name":"width"},"link":null},{"localized_name":"height","name":"height","type":"INT","widget":{"name":"height"},"link":null},{"localized_name":"batch_size","name":"batch_size","type":"INT","widget":{"name":"batch_size"},"link":null}],"outputs":[{"localized_name":"LATENT","name":"LATENT","type":"LATENT","slot_index":0,"links":[2]}],"properties":{"cnr_id":"comfy-core","ver":"0.3.51","Node name for S&R":"EmptyLatentImage"},"widgets_values":[1344,896,4]},{"id":3,"type":"KSampler","pos":[817.3831787109375,214.58123779296875],"size":[315,262],"flags":{},"order":4,"mode":0,"inputs":[{"localized_name":"model","name":"model","type":"MODEL","link":1},{"localized_name":"positive","name":"positive","type":"CONDITIONING","link":25},{"localized_name":"negative","name":"negative","type":"CONDITIONING","link":23},{"localized_name":"latent_image","name":"latent_image","type":"LATENT","link":2},{"localized_name":"seed","name":"seed","type":"INT","widget":{"name":"seed"},"link":null},{"localized_name":"steps","name":"steps","type":"INT","widget":{"name":"steps"},"link":null},{"localized_name":"cfg","name":"cfg","type":"FLOAT","widget":{"name":"cfg"},"link":null},{"localized_name":"sampler_name","name":"sampler_name","type":"COMBO","widget":{"name":"sampler_name"},"link":null},{"localized_name":"scheduler","name":"scheduler","type":"COMBO","widget":{"name":"scheduler"},"link":null},{"localized_name":"denoise","name":"denoise","type":"FLOAT","widget":{"name":"denoise"},"link":null}],"outputs":[{"localized_name":"LATENT","name":"LATENT","type":"LATENT","slot_index":0,"links":[17]}],"properties":{"cnr_id":"comfy-core","ver":"0.3.51","Node name for S&R":"KSampler"},"widgets_values":[854153003003073,"randomize",50,5,"euler_ancestral","beta",1]},{"id":9,"type":"SaveImage","pos":[1339.559326171875,406.1448669433594],"size":[210,270],"flags":{},"order":6,"mode":0,"inputs":[{"localized_name":"images","name":"images","type":"IMAGE","link":9},{"localized_name":"filename_prefix","name":"filename_prefix","type":"STRING","widget":{"name":"filename_prefix"},"link":null}],"outputs":[],"properties":{"cnr_id":"comfy-core","ver":"0.3.51","Node name for S&R":"SaveImage"},"widgets_values":["ComfyUI"]},{"id":7,"type":"CLIPTextEncode","pos":[235.18775939941406,435.5936584472656],"size":[425.27801513671875,180.6060791015625],"flags":{},"order":2,"mode":0,"inputs":[{"localized_name":"clip","name":"clip","type":"CLIP","link":22},{"localized_name":"text","name":"text","type":"STRING","widget":{"name":"text"},"link":null}],"outputs":[{"localized_name":"CONDITIONING","name":"CONDITIONING","type":"CONDITIONING","slot_index":0,"links":[23]}],"properties":{"cnr_id":"comfy-core","ver":"0.3.51","Node name for S&R":"CLIPTextEncode"},"widgets_values":["(worst quality, low quality, normal quality, lowres, low details, oversaturated, undersaturated, overexposed, underexposed, grayscale, bw, bad photo, bad photography, bad art:1.4), (watermark, signature, text font, username, error, logo, words, letters, digits, autograph, trademark, name:1.2), (blur, blurry, grainy), morbid, ugly, asymmetrical, mutated malformed, mutilated, poorly lit, bad shadow, draft, cropped, out of frame, cut off, censored, jpeg artifacts, out of focus, glitch, duplicate, (airbrushed, cartoon, amateur:1.3), (bad hands, bad anatomy, bad body, bad face, bad teeth, bad arms, bad legs, deformities:1.3),\n(different women:1.5), (inconsistent face:1.4), (multiple characters:1.3), different poses, different clothing,\nsepia, bad quality, low quality, blurry"]},{"id":6,"type":"CLIPTextEncode","pos":[250.75006103515625,167.1250762939453],"size":[422.84503173828125,164.31304931640625],"flags":{},"order":3,"mode":0,"inputs":[{"localized_name":"clip","name":"clip","type":"CLIP","link":24},{"localized_name":"text","name":"text","type":"STRING","widget":{"name":"text"},"link":null}],"outputs":[{"localized_name":"CONDITIONING","name":"CONDITIONING","type":"CONDITIONING","slot_index":0,"links":[25]}],"properties":{"cnr_id":"comfy-core","ver":"0.3.51","Node name for S&R":"CLIPTextEncode"},"widgets_values":["character design sheet, concept art, three-view turnaround, pre-teen european girl, long straight hair, kunoichi cloth,deep cleavage, full body, front view + side view + back view, identical facial features, professional character sheet layout, high detail, symmetrical photorealistic face, "]}],"links":[[1,4,0,3,0,"MODEL"],[2,5,0,3,3,"LATENT"],[8,4,2,8,1,"VAE"],[9,8,0,9,0,"IMAGE"],[17,3,0,8,0,"LATENT"],[22,4,1,7,0,"CLIP"],[23,7,0,3,2,"CONDITIONING"],[24,4,1,6,0,"CLIP"],[25,6,0,3,1,"CONDITIONING"]],"groups":[],"config":{},"extra":{"ds":{"scale":2.393920493691638,"offset":[-28.572171249628468,-111.63072023020646]}},"version":0.4}